CONTRIBUTING.md
MANIFEST.in
README.rst
setup.py
docs/HISTORY.txt
docs/LICENSE.GPL
docs/LICENSE.txt
docs/info-docs/howToCreateSparqlWithArguments.rst
docs/info-docs/images/eea.sparql.addnew.png
docs/info-docs/images/eea.sparql.addnewargument.png
docs/info-docs/images/eea.sparql.arguments.png
docs/info-docs/images/eea.sparql.noarguments.png
docs/info-docs/images/eea.sparql.replacearguments.png
docs/info-docs/images/eea.sparql.testquerywithargs.png
docs/info-docs/images/eea.sparql.witharguments.png
eea/__init__.py
eea.sparql.egg-info/PKG-INFO
eea.sparql.egg-info/SOURCES.txt
eea.sparql.egg-info/dependency_links.txt
eea.sparql.egg-info/entry_points.txt
eea.sparql.egg-info/namespace_packages.txt
eea.sparql.egg-info/not-zip-safe
eea.sparql.egg-info/requires.txt
eea.sparql.egg-info/top_level.txt
eea/sparql/README.txt
eea/sparql/__init__.py
eea/sparql/config.py
eea/sparql/configure.zcml
eea/sparql/events.py
eea/sparql/interfaces.py
eea/sparql/permissions.zcml
eea/sparql/profiles.zcml
eea/sparql/skins.zcml
eea/sparql/version.txt
eea/sparql/async/__init__.py
eea/sparql/async/configure.zcml
eea/sparql/async/subscribers.py
eea/sparql/browser/__init__.py
eea/sparql/browser/configure.zcml
eea/sparql/browser/controlpanel.py
eea/sparql/browser/faceted-preview.pt
eea/sparql/browser/schedule_status.pt
eea/sparql/browser/sparql.py
eea/sparql/browser/table-preview.pt
eea/sparql/browser/test_query.pt
eea/sparql/browser/view-bookmarks.pt
eea/sparql/browser/view.pt
eea/sparql/browser/css/datasource.css
eea/sparql/browser/css/view.css
eea/sparql/browser/img/close.png
eea/sparql/browser/img/cloud.png
eea/sparql/browser/img/rdf-icon.gif
eea/sparql/browser/js/datasource.js
eea/sparql/browser/js/view.js
eea/sparql/cache/__init__.py
eea/sparql/cache/cache.py
eea/sparql/cache/configure.zcml
eea/sparql/cache/nocache.py
eea/sparql/content/__init__.py
eea/sparql/content/configure.zcml
eea/sparql/content/events.py
eea/sparql/content/sparql.py
eea/sparql/content/validators.py
eea/sparql/converter/__init__.py
eea/sparql/converter/sparql2json.py
eea/sparql/data/__init__.py
eea/sparql/data/configure.zcml
eea/sparql/data/source.py
eea/sparql/data/tests.py
eea/sparql/locales/eea.pot
eea/sparql/locales/update.sh
eea/sparql/locales/bg/LC_MESSAGES/eea.po
